{
  "kind": "collectionType",
  "collectionName": "software_trusted_bies",
  "info": {
    "singularName": "software-trusted-by",
    "pluralName": "software-trusted-bies",
    "displayName": "Software Trusted By",
    "description": ""
  },
  "options": {
    "draftAndPublish": true
  },
  "attributes": {
    "brand": {
      "type": "string"
    },
    "image": {
      "type": "media",
      "multiple": false,
      "required": false,
      "allowedTypes": [
        "images",
        "files",
        "videos",
        "audios"
      ]
    }
  }
}
